namecheap.py
setup.cfg
setup.py
PyNamecheap.egg-info/PKG-INFO
PyNamecheap.egg-info/SOURCES.txt
PyNamecheap.egg-info/dependency_links.txt
PyNamecheap.egg-info/requires.txt
PyNamecheap.egg-info/top_level.txt