Metadata-Version: 1.1
Name: PyNamecheap
Version: 0.0.3
Summary: Namecheap API client in Python
Home-page: https://github.com/Bemmu/PyNamecheap
Author: Bemmu Sepponen
Author-email: me@bemmu.com
License: MIT
Platform: any
Classifier: Environment :: Web Environment
Classifier: Intended Audience :: Developers
Classifier: License :: OSI Approved :: MIT License
Classifier: Operating System :: OS Independent
Classifier: Programming Language :: Python
Classifier: Topic :: Internet :: WWW/HTTP
Classifier: Topic :: Software Development :: Libraries :: Python Modules
